{
  "entries": [
    {
      "timestamp": "2026-05-19",
      "title": "Explain Mode with In-Page Sub-Selection",
      "description": "在 Translator 内新增 mode='explain' 内置 action,提供通用文本/概念深度解释,并在子选中时切到 explain-fragment-in-context prompt",
      "files": [
        { "action": "new", "path": "docs/atelier/specs/A_explain_mode_with_subselect.md" }
      ]
    },
    {
      "timestamp": "2026-05-21",
      "title": "Customizable Source / Target Language (Lock & Pin)",
      "description": "在 Translator 主界面新增 source/target 各自的 lock 按钮和独立 Detect 按钮；lock 后跳过 detectLang 与 CN↔EN swap，lock 状态与 pin 的语言值持久化到 settings 跨重启保留；不做 per-action lock，writing mode 维持现状",
      "files": [
        { "action": "new", "path": "docs/atelier/specs/B_pinned_source_target_language.md" }
      ]
    },
    {
      "timestamp": "2026-06-10",
      "title": "Translation History Sidebar",
      "description": "在 Tauri 桌面端主翻译窗口新增常驻历史侧边栏：持久化三态位置(左/右/隐藏,首次默认左,按钮循环)、可拖拽调宽并持久化、显示时自动加宽窗口(空间不足则翻译区让位)、内容按当前 action/模式隔离、点记录复用 handleHistoryRestore 加载且不重译、侧边栏头部「弹出」按钮拆为现有独立窗口(可跨 action 浏览,选中后主窗口切到对应 action 加载);仅 Tauri 桌面端,非 Tauri 维持现有 Modal",
      "files": [
        { "action": "new", "path": "docs/atelier/specs/C_translation_history_sidebar.md" }
      ]
    }
  ]
}
